source/basic/conta40F.vhd
library IEEE;
use IEEE.std_logic_1164.all;
use ieee.numeric_std.all;

entity conta40F is
	port(
     clk : in std_logic;
     reset : in std_logic; -- Pausa el conteo con reset=1
     count_o : out std_logic_vector(3 downto 0);
     end_o   : out std_logic -- Alto cuando termina una cuenta
);
end entity;


architecture behavioral of conta40F is
    signal cuenta : integer range 0 to 15;

begin
    process(clk,reset)
    begin
    	if (reset='1') then
            cuenta <= 0;
            end_o <= '0';
        elsif(clk='1') then
            end_o <= '0';
            if(cuenta=15) then
                cuenta <= 0;
                end_o <= '1';
            else    
                cuenta <= cuenta + 1;
            end if;    
        end if;
    end process;
    --Converts from dec to 8 bits bin
    count_o <= std_logic_vector(to_unsigned(cuenta, 4));

end architecture;

source/sims/testbench/conta40F_tb.vhd
library ieee;
use ieee.std_logic_1164.all;
use work.basic_devs.conta40F;

entity conta40F_tb is
end entity;

architecture behavioral of conta40F_tb is
	signal clk:std_logic:='1';
	signal reset: std_logic:='0';
	signal out_signal: std_logic_vector(3 downto 0);
	signal end_o: std_logic;

begin
	clk <= not(clk) after 2 ns;
	reset <= not(reset) after 800 ns;

	conta_0F: conta40F port map(clk,reset,out_signal,end_o);
end architecture;

source/sims/vcd/conta40F_sim.vcd
$date
  Mon Apr 20 14:47:05 2020
$end
$version
  GHDL v0
$end
$timescale
  1 fs
$end
$scope module standard $end
$upscope $end
$scope module std_logic_1164 $end
$upscope $end
$scope module basic_devs $end
$upscope $end
$scope module numeric_std $end
$upscope $end
$scope module conta40f_tb $end
$var reg 1 ! clk $end
$var reg 1 " reset $end
$var reg 4 # out_signal[3:0] $end
$var reg 1 $ end_o $end
$scope module conta_0f $end
$var reg 1 % clk $end
$var reg 1 & reset $end
$var reg 4 ' count_o[3:0] $end
$var reg 1 ( end_o $end
$var integer 32 ) cuenta $end
$upscope $end
$upscope $end
$enddefinitions $end
#0
1!
0"
b0000 #
U$
1%
0&
b0000 '
U(
b0 )
#2000000
0!
0%
#4000000
1!
b0001 #
0$
1%
b0001 '
0(
b1 )
#6000000
0!
0%
#8000000
1!
b0010 #
1%
b0010 '
b10 )
#10000000
0!
0%
#12000000
1!
b0011 #
1%
b0011 '
b11 )
#14000000
0!
0%
#16000000
1!
b0100 #
1%
b0100 '
b100 )
#18000000
0!
0%
#20000000
1!
b0101 #
1%
b0101 '
b101 )
#22000000
0!
0%
#24000000
1!
b0110 #
1%
b0110 '
b110 )
#26000000
0!
0%
#28000000
1!
b0111 #
1%
b0111 '
b111 )
#30000000
0!
0%
#32000000
1!
b1000 #
1%
b1000 '
b1000 )
#34000000
0!
0%
#36000000
1!
b1001 #
1%
b1001 '
b1001 )
#38000000
0!
0%
#40000000
1!
b1010 #
1%
b1010 '
b1010 )
#42000000
0!
0%
#44000000
1!
b1011 #
1%
b1011 '
b1011 )
#46000000
0!
0%
#48000000
1!
b1100 #
1%
b1100 '
b1100 )
#50000000
0!
0%
#52000000
1!
b1101 #
1%
b1101 '
b1101 )
#54000000
0!
0%
#56000000
1!
b1110 #
1%
b1110 '
b1110 )
#58000000
0!
0%
#60000000
1!
b1111 #
1%
b1111 '
b1111 )
#62000000
0!
0%
#64000000
1!
b0000 #
1$
1%
b0000 '
1(
b0 )
#66000000
0!
0%
#68000000
1!
b0001 #
0$
1%
b0001 '
0(
b1 )
#70000000
0!
0%
#72000000
1!
b0010 #
1%
b0010 '
b10 )
#74000000
0!
0%
#76000000
1!
b0011 #
1%
b0011 '
b11 )
#78000000
0!
0%
#80000000
1!
b0100 #
1%
b0100 '
b100 )
#82000000
0!
0%
#84000000
1!
b0101 #
1%
b0101 '
b101 )
#86000000
0!
0%
#88000000
1!
b0110 #
1%
b0110 '
b110 )
#90000000
0!
0%
#92000000
1!
b0111 #
1%
b0111 '
b111 )
#94000000
0!
0%
#96000000
1!
b1000 #
1%
b1000 '
b1000 )
#98000000
0!
0%
#100000000
1!
b1001 #
1%
b1001 '
b1001 )
#102000000
0!
0%
#104000000
1!
b1010 #
1%
b1010 '
b1010 )
#106000000
0!
0%
#108000000
1!
b1011 #
1%
b1011 '
b1011 )
#110000000
0!
0%
#112000000
1!
b1100 #
1%
b1100 '
b1100 )
#114000000
0!
0%
#116000000
1!
b1101 #
1%
b1101 '
b1101 )
#118000000
0!
0%
#120000000
1!
b1110 #
1%
b1110 '
b1110 )
#122000000
0!
0%
#124000000
1!
b1111 #
1%
b1111 '
b1111 )
#126000000
0!
0%
#128000000
1!
b0000 #
1$
1%
b0000 '
1(
b0 )
#130000000
0!
0%
#132000000
1!
b0001 #
0$
1%
b0001 '
0(
b1 )
#134000000
0!
0%
#136000000
1!
b0010 #
1%
b0010 '
b10 )
#138000000
0!
0%
#140000000
1!
b0011 #
1%
b0011 '
b11 )
#142000000
0!
0%
#144000000
1!
b0100 #
1%
b0100 '
b100 )
#146000000
0!
0%
#148000000
1!
b0101 #
1%
b0101 '
b101 )
#150000000
0!
0%
#152000000
1!
b0110 #
1%
b0110 '
b110 )
#154000000
0!
0%
#156000000
1!
b0111 #
1%
b0111 '
b111 )
#158000000
0!
0%
#160000000
1!
b1000 #
1%
b1000 '
b1000 )
#162000000
0!
0%
#164000000
1!
b1001 #
1%
b1001 '
b1001 )
#166000000
0!
0%
#168000000
1!
b1010 #
1%
b1010 '
b1010 )
#170000000
0!
0%
#172000000
1!
b1011 #
1%
b1011 '
b1011 )
#174000000
0!
0%
#176000000
1!
b1100 #
1%
b1100 '
b1100 )
#178000000
0!
0%
#180000000
1!
b1101 #
1%
b1101 '
b1101 )
#182000000
0!
0%
#184000000
1!
b1110 #
1%
b1110 '
b1110 )
#186000000
0!
0%
#188000000
1!
b1111 #
1%
b1111 '
b1111 )
#190000000
0!
0%
#192000000
1!
b0000 #
1$
1%
b0000 '
1(
b0 )
#194000000
0!
0%
#196000000
1!
b0001 #
0$
1%
b0001 '
0(
b1 )
#198000000
0!
0%
#200000000
1!
b0010 #
1%
b0010 '
b10 )
#202000000
0!
0%
#204000000
1!
b0011 #
1%
b0011 '
b11 )
#206000000
0!
0%
#208000000
1!
b0100 #
1%
b0100 '
b100 )
#210000000
0!
0%
#212000000
1!
b0101 #
1%
b0101 '
b101 )
#214000000
0!
0%
#216000000
1!
b0110 #
1%
b0110 '
b110 )
#218000000
0!
0%
#220000000
1!
b0111 #
1%
b0111 '
b111 )
#222000000
0!
0%
#224000000
1!
b1000 #
1%
b1000 '
b1000 )
#226000000
0!
0%
#228000000
1!
b1001 #
1%
b1001 '
b1001 )
#230000000
0!
0%
#232000000
1!
b1010 #
1%
b1010 '
b1010 )
#234000000
0!
0%
#236000000
1!
b1011 #
1%
b1011 '
b1011 )
#238000000
0!
0%
#240000000
1!
b1100 #
1%
b1100 '
b1100 )
#242000000
0!
0%
#244000000
1!
b1101 #
1%
b1101 '
b1101 )
#246000000
0!
0%
#248000000
1!
b1110 #
1%
b1110 '
b1110 )
#250000000
0!
0%
#252000000
1!
b1111 #
1%
b1111 '
b1111 )
#254000000
0!
0%
#256000000
1!
b0000 #
1$
1%
b0000 '
1(
b0 )
#258000000
0!
0%
#260000000
1!
b0001 #
0$
1%
b0001 '
0(
b1 )
#262000000
0!
0%
#264000000
1!
b0010 #
1%
b0010 '
b10 )
#266000000
0!
0%
#268000000
1!
b0011 #
1%
b0011 '
b11 )
#270000000
0!
0%
#272000000
1!
b0100 #
1%
b0100 '
b100 )
#274000000
0!
0%
#276000000
1!
b0101 #
1%
b0101 '
b101 )
#278000000
0!
0%
#280000000
1!
b0110 #
1%
b0110 '
b110 )
#282000000
0!
0%
#284000000
1!
b0111 #
1%
b0111 '
b111 )
#286000000
0!
0%
#288000000
1!
b1000 #
1%
b1000 '
b1000 )
#290000000
0!
0%
#292000000
1!
b1001 #
1%
b1001 '
b1001 )
#294000000
0!
0%
#296000000
1!
b1010 #
1%
b1010 '
b1010 )
#298000000
0!
0%
#300000000
1!
b1011 #
1%
b1011 '
b1011 )
#302000000
0!
0%
#304000000
1!
b1100 #
1%
b1100 '
b1100 )
#306000000
0!
0%
#308000000
1!
b1101 #
1%
b1101 '
b1101 )
#310000000
0!
0%
#312000000
1!
b1110 #
1%
b1110 '
b1110 )
#314000000
0!
0%
#316000000
1!
b1111 #
1%
b1111 '
b1111 )
#318000000
0!
0%
#320000000
1!
b0000 #
1$
1%
b0000 '
1(
b0 )
#322000000
0!
0%
#324000000
1!
b0001 #
0$
1%
b0001 '
0(
b1 )
#326000000
0!
0%
#328000000
1!
b0010 #
1%
b0010 '
b10 )
#330000000
0!
0%
#332000000
1!
b0011 #
1%
b0011 '
b11 )
#334000000
0!
0%
#336000000
1!
b0100 #
1%
b0100 '
b100 )
#338000000
0!
0%
#340000000
1!
b0101 #
1%
b0101 '
b101 )
#342000000
0!
0%
#344000000
1!
b0110 #
1%
b0110 '
b110 )
#346000000
0!
0%
#348000000
1!
b0111 #
1%
b0111 '
b111 )
#350000000
0!
0%
#352000000
1!
b1000 #
1%
b1000 '
b1000 )
#354000000
0!
0%
#356000000
1!
b1001 #
1%
b1001 '
b1001 )
#358000000
0!
0%
#360000000
1!
b1010 #
1%
b1010 '
b1010 )
#362000000
0!
0%
#364000000
1!
b1011 #
1%
b1011 '
b1011 )
#366000000
0!
0%
#368000000
1!
b1100 #
1%
b1100 '
b1100 )
#370000000
0!
0%
#372000000
1!
b1101 #
1%
b1101 '
b1101 )
#374000000
0!
0%
#376000000
1!
b1110 #
1%
b1110 '
b1110 )
#378000000
0!
0%
#380000000
1!
b1111 #
1%
b1111 '
b1111 )
#382000000
0!
0%
#384000000
1!
b0000 #
1$
1%
b0000 '
1(
b0 )
#386000000
0!
0%
#388000000
1!
b0001 #
0$
1%
b0001 '
0(
b1 )
#390000000
0!
0%
#392000000
1!
b0010 #
1%
b0010 '
b10 )
#394000000
0!
0%
#396000000
1!
b0011 #
1%
b0011 '
b11 )
#398000000
0!
0%
#400000000
1!
b0100 #
1%
b0100 '
b100 )
#402000000
0!
0%
#404000000
1!
b0101 #
1%
b0101 '
b101 )
#406000000
0!
0%
#408000000
1!
b0110 #
1%
b0110 '
b110 )
#410000000
0!
0%
#412000000
1!
b0111 #
1%
b0111 '
b111 )
#414000000
0!
0%
#416000000
1!
b1000 #
1%
b1000 '
b1000 )
#418000000
0!
0%
#420000000
1!
b1001 #
1%
b1001 '
b1001 )
#422000000
0!
0%
#424000000
1!
b1010 #
1%
b1010 '
b1010 )
#426000000
0!
0%
#428000000
1!
b1011 #
1%
b1011 '
b1011 )
#430000000
0!
0%
#432000000
1!
b1100 #
1%
b1100 '
b1100 )
#434000000
0!
0%
#436000000
1!
b1101 #
1%
b1101 '
b1101 )
#438000000
0!
0%
#440000000
1!
b1110 #
1%
b1110 '
b1110 )
#442000000
0!
0%
#444000000
1!
b1111 #
1%
b1111 '
b1111 )
#446000000
0!
0%
#448000000
1!
b0000 #
1$
1%
b0000 '
1(
b0 )
#450000000
0!
0%
#452000000
1!
b0001 #
0$
1%
b0001 '
0(
b1 )
#454000000
0!
0%
#456000000
1!
b0010 #
1%
b0010 '
b10 )
#458000000
0!
0%
#460000000
1!
b0011 #
1%
b0011 '
b11 )
#462000000
0!
0%
#464000000
1!
b0100 #
1%
b0100 '
b100 )
#466000000
0!
0%
#468000000
1!
b0101 #
1%
b0101 '
b101 )
#470000000
0!
0%
#472000000
1!
b0110 #
1%
b0110 '
b110 )
#474000000
0!
0%
#476000000
1!
b0111 #
1%
b0111 '
b111 )
#478000000
0!
0%
#480000000
1!
b1000 #
1%
b1000 '
b1000 )
#482000000
0!
0%
#484000000
1!
b1001 #
1%
b1001 '
b1001 )
#486000000
0!
0%
#488000000
1!
b1010 #
1%
b1010 '
b1010 )
#490000000
0!
0%
#492000000
1!
b1011 #
1%
b1011 '
b1011 )
#494000000
0!
0%
#496000000
1!
b1100 #
1%
b1100 '
b1100 )
#498000000
0!
0%
#500000000
1!
b1101 #
1%
b1101 '
b1101 )
#502000000
0!
0%
#504000000
1!
b1110 #
1%
b1110 '
b1110 )
#506000000
0!
0%
#508000000
1!
b1111 #
1%
b1111 '
b1111 )
#510000000
0!
0%
#512000000
1!
b0000 #
1$
1%
b0000 '
1(
b0 )
#514000000
0!
0%
#516000000
1!
b0001 #
0$
1%
b0001 '
0(
b1 )
#518000000
0!
0%
#520000000
1!
b0010 #
1%
b0010 '
b10 )
#522000000
0!
0%
#524000000
1!
b0011 #
1%
b0011 '
b11 )
#526000000
0!
0%
#528000000
1!
b0100 #
1%
b0100 '
b100 )
#530000000
0!
0%
#532000000
1!
b0101 #
1%
b0101 '
b101 )
#534000000
0!
0%
#536000000
1!
b0110 #
1%
b0110 '
b110 )
#538000000
0!
0%
#540000000
1!
b0111 #
1%
b0111 '
b111 )
#542000000
0!
0%
#544000000
1!
b1000 #
1%
b1000 '
b1000 )
#546000000
0!
0%
#548000000
1!
b1001 #
1%
b1001 '
b1001 )
#550000000
0!
0%
#552000000
1!
b1010 #
1%
b1010 '
b1010 )
#554000000
0!
0%
#556000000
1!
b1011 #
1%
b1011 '
b1011 )
#558000000
0!
0%
#560000000
1!
b1100 #
1%
b1100 '
b1100 )
#562000000
0!
0%
#564000000
1!
b1101 #
1%
b1101 '
b1101 )
#566000000
0!
0%
#568000000
1!
b1110 #
1%
b1110 '
b1110 )
#570000000
0!
0%
#572000000
1!
b1111 #
1%
b1111 '
b1111 )
#574000000
0!
0%
#576000000
1!
b0000 #
1$
1%
b0000 '
1(
b0 )
#578000000
0!
0%
#580000000
1!
b0001 #
0$
1%
b0001 '
0(
b1 )
#582000000
0!
0%
#584000000
1!
b0010 #
1%
b0010 '
b10 )
#586000000
0!
0%
#588000000
1!
b0011 #
1%
b0011 '
b11 )
#590000000
0!
0%
#592000000
1!
b0100 #
1%
b0100 '
b100 )
#594000000
0!
0%
#596000000
1!
b0101 #
1%
b0101 '
b101 )
#598000000
0!
0%
#600000000
1!
b0110 #
1%
b0110 '
b110 )
#602000000
0!
0%
#604000000
1!
b0111 #
1%
b0111 '
b111 )
#606000000
0!
0%
#608000000
1!
b1000 #
1%
b1000 '
b1000 )
#610000000
0!
0%
#612000000
1!
b1001 #
1%
b1001 '
b1001 )
#614000000
0!
0%
#616000000
1!
b1010 #
1%
b1010 '
b1010 )
#618000000
0!
0%
#620000000
1!
b1011 #
1%
b1011 '
b1011 )
#622000000
0!
0%
#624000000
1!
b1100 #
1%
b1100 '
b1100 )
#626000000
0!
0%
#628000000
1!
b1101 #
1%
b1101 '
b1101 )
#630000000
0!
0%
#632000000
1!
b1110 #
1%
b1110 '
b1110 )
#634000000
0!
0%
#636000000
1!
b1111 #
1%
b1111 '
b1111 )
#638000000
0!
0%
#640000000
1!
b0000 #
1$
1%
b0000 '
1(
b0 )
#642000000
0!
0%
#644000000
1!
b0001 #
0$
1%
b0001 '
0(
b1 )
#646000000
0!
0%
#648000000
1!
b0010 #
1%
b0010 '
b10 )
#650000000
0!
0%
#652000000
1!
b0011 #
1%
b0011 '
b11 )
#654000000
0!
0%
#656000000
1!
b0100 #
1%
b0100 '
b100 )
#658000000
0!
0%
#660000000
1!
b0101 #
1%
b0101 '
b101 )
#662000000
0!
0%
#664000000
1!
b0110 #
1%
b0110 '
b110 )
#666000000
0!
0%
#668000000
1!
b0111 #
1%
b0111 '
b111 )
#670000000
0!
0%
#672000000
1!
b1000 #
1%
b1000 '
b1000 )
#674000000
0!
0%
#676000000
1!
b1001 #
1%
b1001 '
b1001 )
#678000000
0!
0%
#680000000
1!
b1010 #
1%
b1010 '
b1010 )
#682000000
0!
0%
#684000000
1!
b1011 #
1%
b1011 '
b1011 )
#686000000
0!
0%
#688000000
1!
b1100 #
1%
b1100 '
b1100 )
#690000000
0!
0%
#692000000
1!
b1101 #
1%
b1101 '
b1101 )
#694000000
0!
0%
#696000000
1!
b1110 #
1%
b1110 '
b1110 )
#698000000
0!
0%
#700000000
1!
b1111 #
1%
b1111 '
b1111 )
#702000000
0!
0%
#704000000
1!
b0000 #
1$
1%
b0000 '
1(
b0 )
#706000000
0!
0%
#708000000
1!
b0001 #
0$
1%
b0001 '
0(
b1 )
#710000000
0!
0%
#712000000
1!
b0010 #
1%
b0010 '
b10 )
#714000000
0!
0%
#716000000
1!
b0011 #
1%
b0011 '
b11 )
#718000000
0!
0%
#720000000
1!
b0100 #
1%
b0100 '
b100 )
#722000000
0!
0%
#724000000
1!
b0101 #
1%
b0101 '
b101 )
#726000000
0!
0%
#728000000
1!
b0110 #
1%
b0110 '
b110 )
#730000000
0!
0%
#732000000
1!
b0111 #
1%
b0111 '
b111 )
#734000000
0!
0%
#736000000
1!
b1000 #
1%
b1000 '
b1000 )
#738000000
0!
0%
#740000000
1!
b1001 #
1%
b1001 '
b1001 )
#742000000
0!
0%
#744000000
1!
b1010 #
1%
b1010 '
b1010 )
#746000000
0!
0%
#748000000
1!
b1011 #
1%
b1011 '
b1011 )
#750000000
0!
0%
#752000000
1!
b1100 #
1%
b1100 '
b1100 )
#754000000
0!
0%
#756000000
1!
b1101 #
1%
b1101 '
b1101 )
#758000000
0!
0%
#760000000
1!
b1110 #
1%
b1110 '
b1110 )
#762000000
0!
0%
#764000000
1!
b1111 #
1%
b1111 '
b1111 )
#766000000
0!
0%
#768000000
1!
b0000 #
1$
1%
b0000 '
1(
b0 )
#770000000
0!
0%
#772000000
1!
b0001 #
0$
1%
b0001 '
0(
b1 )
#774000000
0!
0%
#776000000
1!
b0010 #
1%
b0010 '
b10 )
#778000000
0!
0%
#780000000
1!
b0011 #
1%
b0011 '
b11 )
#782000000
0!
0%
#784000000
1!
b0100 #
1%
b0100 '
b100 )
#786000000
0!
0%
#788000000
1!
b0101 #
1%
b0101 '
b101 )
#790000000
0!
0%
#792000000
1!
b0110 #
1%
b0110 '
b110 )
#794000000
0!
0%
#796000000
1!
b0111 #
1%
b0111 '
b111 )
#798000000
0!
0%
#800000000
1!
1"
b0000 #
1%
1&
b0000 '
b0 )
