source/basic/conta305.vhd
library ieee;
use ieee.std_logic_1164.all;

entity conta305 is
	port (
	 clk: in std_logic;
	 count: out std_logic_vector(2 downto 0)
  );
end entity;

architecture behavioral of conta305 is
	signal delta: std_logic_vector(2 downto 0):="000";
begin
	process(clk)
	begin
		if(clk='1') then
			delta <=
			((not delta(2) and delta(1) and delta(0)) or (delta(2) and not delta(0) and not delta(1))) & 
			(not delta(2) and (delta(0) xor delta(1))) & 
			(not delta(0) and (not delta(1) or not delta(2)));
			count <= delta;
		end if;
	end process;
end architecture;

source/sims/testbench/conta305_tb.vhd
library ieee;
use ieee.std_logic_1164.all;
use work.basic_devs.conta305; -- Incluímos el componente desde basic_devs

entity conta305_tb is -- Caja cerrada
end entity;

architecture conta305_test of conta305_tb is
	signal clk: std_logic:='0'; -- Señal de reloj
	signal out_cont: std_logic_vector(2 downto 0); -- Señal a conectar a la salida del contador
begin
	clk <= not(clk) after 1 ns; -- Simulamos un ciclo de reloj de 2 ns
	conta305_block: conta305 port map(clk, out_cont); -- Instanciamos el contador
end architecture;

source/sims/vcd/conta305_sim.vcd
$date
  Tue Apr 21 23:59:16 2020
$end
$version
  GHDL v0
$end
$timescale
  1 fs
$end
$scope module standard $end
$upscope $end
$scope module std_logic_1164 $end
$upscope $end
$scope module basic_devs $end
$upscope $end
$scope module conta305_tb $end
$var reg 1 ! clk $end
$var reg 3 " out_cont[2:0] $end
$scope module conta305_block $end
$var reg 1 # clk $end
$var reg 3 $ count[2:0] $end
$var reg 3 % delta[2:0] $end
$upscope $end
$upscope $end
$enddefinitions $end
#0
0!
bUUU "
0#
bUUU $
b000 %
#1000000
1!
b000 "
1#
b000 $
b001 %
#2000000
0!
0#
#3000000
1!
b001 "
1#
b001 $
b010 %
#4000000
0!
0#
#5000000
1!
b010 "
1#
b010 $
b011 %
#6000000
0!
0#
#7000000
1!
b011 "
1#
b011 $
b100 %
#8000000
0!
0#
#9000000
1!
b100 "
1#
b100 $
b101 %
#10000000
0!
0#
#11000000
1!
b101 "
1#
b101 $
b000 %
#12000000
0!
0#
#13000000
1!
b000 "
1#
b000 $
b001 %
#14000000
0!
0#
#15000000
1!
b001 "
1#
b001 $
b010 %
#16000000
0!
0#
#17000000
1!
b010 "
1#
b010 $
b011 %
#18000000
0!
0#
#19000000
1!
b011 "
1#
b011 $
b100 %
#20000000
0!
0#
#21000000
1!
b100 "
1#
b100 $
b101 %
#22000000
0!
0#
#23000000
1!
b101 "
1#
b101 $
b000 %
#24000000
0!
0#
#25000000
1!
b000 "
1#
b000 $
b001 %
#26000000
0!
0#
#27000000
1!
b001 "
1#
b001 $
b010 %
#28000000
0!
0#
#29000000
1!
b010 "
1#
b010 $
b011 %
#30000000
0!
0#
#31000000
1!
b011 "
1#
b011 $
b100 %
#32000000
0!
0#
#33000000
1!
b100 "
1#
b100 $
b101 %
#34000000
0!
0#
#35000000
1!
b101 "
1#
b101 $
b000 %
#36000000
0!
0#
#37000000
1!
b000 "
1#
b000 $
b001 %
#38000000
0!
0#
#39000000
1!
b001 "
1#
b001 $
b010 %
#40000000
0!
0#
#41000000
1!
b010 "
1#
b010 $
b011 %
#42000000
0!
0#
#43000000
1!
b011 "
1#
b011 $
b100 %
#44000000
0!
0#
#45000000
1!
b100 "
1#
b100 $
b101 %
#46000000
0!
0#
#47000000
1!
b101 "
1#
b101 $
b000 %
#48000000
0!
0#
#49000000
1!
b000 "
1#
b000 $
b001 %
#50000000
0!
0#
#51000000
1!
b001 "
1#
b001 $
b010 %
#52000000
0!
0#
#53000000
1!
b010 "
1#
b010 $
b011 %
#54000000
0!
0#
#55000000
1!
b011 "
1#
b011 $
b100 %
#56000000
0!
0#
#57000000
1!
b100 "
1#
b100 $
b101 %
#58000000
0!
0#
#59000000
1!
b101 "
1#
b101 $
b000 %
#60000000
0!
0#
#61000000
1!
b000 "
1#
b000 $
b001 %
#62000000
0!
0#
#63000000
1!
b001 "
1#
b001 $
b010 %
#64000000
0!
0#
#65000000
1!
b010 "
1#
b010 $
b011 %
#66000000
0!
0#
#67000000
1!
b011 "
1#
b011 $
b100 %
#68000000
0!
0#
#69000000
1!
b100 "
1#
b100 $
b101 %
#70000000
0!
0#
#71000000
1!
b101 "
1#
b101 $
b000 %
#72000000
0!
0#
#73000000
1!
b000 "
1#
b000 $
b001 %
#74000000
0!
0#
#75000000
1!
b001 "
1#
b001 $
b010 %
#76000000
0!
0#
#77000000
1!
b010 "
1#
b010 $
b011 %
#78000000
0!
0#
#79000000
1!
b011 "
1#
b011 $
b100 %
#80000000
0!
0#
#81000000
1!
b100 "
1#
b100 $
b101 %
#82000000
0!
0#
#83000000
1!
b101 "
1#
b101 $
b000 %
#84000000
0!
0#
#85000000
1!
b000 "
1#
b000 $
b001 %
#86000000
0!
0#
#87000000
1!
b001 "
1#
b001 $
b010 %
#88000000
0!
0#
#89000000
1!
b010 "
1#
b010 $
b011 %
#90000000
0!
0#
#91000000
1!
b011 "
1#
b011 $
b100 %
#92000000
0!
0#
#93000000
1!
b100 "
1#
b100 $
b101 %
#94000000
0!
0#
#95000000
1!
b101 "
1#
b101 $
b000 %
#96000000
0!
0#
#97000000
1!
b000 "
1#
b000 $
b001 %
#98000000
0!
0#
#99000000
1!
b001 "
1#
b001 $
b010 %
